knowgraph/__init__.py
knowgraph/config.py
knowgraph/version.py
knowgraph/adapters/__init__.py
knowgraph/adapters/api/__init__.py
knowgraph/adapters/cli/__init__.py
knowgraph/adapters/cli/discover_conversations_command.py
knowgraph/adapters/cli/index_command.py
knowgraph/adapters/cli/index_helpers.py
knowgraph/adapters/cli/main.py
knowgraph/adapters/cli/query_command.py
knowgraph/adapters/cli/update_command.py
knowgraph/adapters/cli/version_command.py
knowgraph/adapters/mcp/__init__.py
knowgraph/adapters/mcp/diagnostic_handler.py
knowgraph/adapters/mcp/handlers.py
knowgraph/adapters/mcp/methods.py
knowgraph/adapters/mcp/server.py
knowgraph/adapters/mcp/utils.py
knowgraph/adapters/mcp/version_handlers.py
knowgraph/adapters/mcp/version_methods.py
knowgraph/application/__init__.py
knowgraph/application/analysis/call_graph_analyzer.py
knowgraph/application/analysis/dominance_analyzer.py
knowgraph/application/analysis/joern_repl.py
knowgraph/application/analytics/__init__.py
knowgraph/application/analytics/knowledge_tracker.py
knowgraph/application/analytics/topic_analyzer.py
knowgraph/application/evolution/__init__.py
knowgraph/application/evolution/incremental_update.py
knowgraph/application/indexing/__init__.py
knowgraph/application/indexing/graph_builder.py
knowgraph/application/indexing/post_index_hooks.py
knowgraph/application/linking/__init__.py
knowgraph/application/linking/conversation_linker.py
knowgraph/application/query/code_query_handler.py
knowgraph/application/query/query_classifier.py
knowgraph/application/querying/__init__.py
knowgraph/application/querying/centrality_mp.py
knowgraph/application/querying/context_assembly.py
knowgraph/application/querying/conversation_search.py
knowgraph/application/querying/explanation.py
knowgraph/application/querying/hierarchical_lifting.py
knowgraph/application/querying/impact_analyzer.py
knowgraph/application/querying/query_engine.py
knowgraph/application/querying/query_expansion.py
knowgraph-1.0.0.dist-info/licenses/LICENSE
knowgraph-1.0.0.dist-info/METADATA
knowgraph-1.0.0.dist-info/WHEEL
knowgraph-1.0.0.dist-info/entry_points.txt
knowgraph-1.0.0.dist-info/top_level.txt
knowgraph-1.0.0.dist-info/RECORD
