Metadata-Version: 2.4
Name: knowgraph
Version: 1.0.0
Summary: Knowledge Graph-Powered RAG system with enterprise resilience patterns
Author-email: Yunus Güngör <mail@yunusgungor.com>
License: MIT
Project-URL: Homepage, https://github.com/yunusgungor/knowgraph
Project-URL: Documentation, https://github.com/yunusgungor/knowgraph/docs
Project-URL: Repository, https://github.com/yunusgungor/knowgraph
Project-URL: Issues, https://github.com/yunusgungor/knowgraph/issues
Keywords: graph,rag,code-analysis,knowledge-graph,ml
Classifier: Development Status :: 3 - Alpha
Classifier: Intended Audience :: Developers
Classifier: License :: OSI Approved :: MIT License
Classifier: Programming Language :: Python :: 3
Classifier: Programming Language :: Python :: 3.10
Classifier: Programming Language :: Python :: 3.11
Classifier: Programming Language :: Python :: 3.12
Classifier: Topic :: Software Development :: Libraries :: Python Modules
Classifier: Topic :: Scientific/Engineering :: Artificial Intelligence
Requires-Python: >=3.10
License-File: LICENSE
Requires-Dist: numpy>=1.26.0
Requires-Dist: scipy>=1.11.0
Requires-Dist: networkx>=3.2.0
Requires-Dist: click>=8.1.0
Requires-Dist: rich>=13.7.0
Requires-Dist: tqdm>=4.66.0
Requires-Dist: mcp>=1.0.0
Requires-Dist: openai>=1.0.0
Requires-Dist: python-dotenv>=1.0.0
Requires-Dist: tiktoken>=0.5.0
Requires-Dist: gitingest>=0.3.1
Requires-Dist: tenacity>=8.2.0
Requires-Dist: psutil>=5.9.0
Requires-Dist: aiofiles>=23.2.0
Provides-Extra: dev
Requires-Dist: pytest>=7.4.0; extra == "dev"
Requires-Dist: pytest-cov>=4.1.0; extra == "dev"
Requires-Dist: pytest-mock>=3.12.0; extra == "dev"
Requires-Dist: pytest-asyncio>=0.23.0; extra == "dev"
Requires-Dist: pytest-xdist>=3.5.0; extra == "dev"
Requires-Dist: black>=24.1.0; extra == "dev"
Requires-Dist: isort>=5.13.0; extra == "dev"
Requires-Dist: flake8>=7.0.0; extra == "dev"
Requires-Dist: pylint>=3.0.0; extra == "dev"
Requires-Dist: mypy>=1.8.0; extra == "dev"
Requires-Dist: ruff>=0.1.0; extra == "dev"
Requires-Dist: pre-commit>=3.6.0; extra == "dev"
Requires-Dist: ipdb>=0.13.0; extra == "dev"
Requires-Dist: jupyterlab>=4.0.0; extra == "dev"
Requires-Dist: sphinx>=7.2.0; extra == "dev"
Requires-Dist: sphinx-rtd-theme>=2.0.0; extra == "dev"
Dynamic: license-file
